[
  {
    "title": "Beer Den & SausageWorks Brats Pairing",
    "location": "Store 12",
    "start": "2026-03-08T17:30:00",
    "end": "2026-03-08T19:00:00",
    "description": "Try our new 'The Farmers Daughter' + get 10% off your next purchase."
  },
  {
    "title": "Pick & Prep Charcuterie Tray Builds",
    "location": "Store 7",
    "start": "2026-03-14T10:00:00",
    "end": "2026-03-14T11:30:00",
    "description": "Free event. Supplies included while they last."
  },
  {
    "title": "Breadcrumb Sourdough Bread Making",
    "location": "Store 5",
    "start": "2026-03-21T12:00:00",
    "end": "2026-03-21T14:00:00",
    "description": "Learn to make starter, and how to bake sourdough."
  }
]
